[
  {
    "id": "12f68f25-1797-4609-995c-326d301bd24c",
    "title": "프레젠테이션",
    "startDate": "2025-07-09T15:17:36",
    "endDate": "2025-07-09T16:17:36",
    "createdAt": "2025-06-22T15:17:36",
    "updatedAt": "2025-07-08T15:17:36",
    "backgroundColor": "pink",
    "isAllDay": false,
    "repeatRule": "매월",
    "hasRepeatEndDate": true,
    "repeatEndDate": "2025-08-12T15:17:36",
    "isCompleted": true
  },
  {
    "id": "f8d6fdda-a793-449b-87e4-b9eaa524faa9",
    "title": "수영",
    "startDate": "2025-07-10T16:20:22",
    "endDate": "2025-07-10T17:20:22",
    "createdAt": "2025-06-14T16:20:22",
    "updatedAt": "2025-07-09T16:20:22",
    "backgroundColor": "yellow",
    "isAllDay": false,
    "repeatRule": "매월",
    "hasRepeatEndDate": true,
    "repeatEndDate": "2025-08-19T16:20:22",
    "isCompleted": true
  },
  {
    "id": "970444e4-4785-4896-86b7-83f3f34aa34b",
    "title": "등산",
    "startDate": "2025-07-13T11:54:07",
    "endDate": "2025-07-13T13:54:07",
    "createdAt": "2025-06-16T11:54:07",
    "updatedAt": "2025-07-11T11:54:07",
    "backgroundColor": "orange",
    "isAllDay": false,
    "repeatRule": null,
    "hasRepeatEndDate": false,
    "repeatEndDate": null,
    "isCompleted": true
  },
  {
    "id": "ffbd43b2-b92f-4d35-975a-31abcf2342ed",
    "title": "산책",
    "startDate": "2025-07-29T01:44:42",
    "endDate": "2025-07-29T04:44:42",
    "createdAt": "2025-07-15T01:44:42",
    "updatedAt": "2025-07-29T01:44:42",
    "backgroundColor": "green",
    "isAllDay": false,
    "repeatRule": "매주",
    "hasRepeatEndDate": true,
    "repeatEndDate": "2025-08-29T01:44:42",
    "isCompleted": false
  },
  {
    "id": "72915f36-1ff5-4d64-a5a8-a56013d63b2d",
    "title": "빨래",
    "startDate": "2025-07-15T23:41:20",
    "endDate": "2025-07-16T01:41:20",
    "createdAt": "2025-06-22T23:41:20",
    "updatedAt": "2025-07-13T23:41:20",
    "backgroundColor": "red",
    "isAllDay": false,
    "repeatRule": "매월",
    "hasRepeatEndDate": false,
    "repeatEndDate": null,
    "isCompleted": false
  },
  {
    "id": "afc6c9be-6745-4951-a848-90f944831713",
    "title": "수영",
    "startDate": "2025-06-11T06:43:57",
    "endDate": "2025-06-11T09:43:57",
    "createdAt": "2025-05-15T06:43:57",
    "updatedAt": "2025-06-11T06:43:57",
    "backgroundColor": "red",
    "isAllDay": false,
    "repeatRule": "매일",
    "hasRepeatEndDate": false,
    "repeatEndDate": null,
    "isCompleted": true
  },
  {
    "id": "65d8e1a1-7683-40af-9ef7-9ff774655b4a",
    "title": "빨래",
    "startDate": "2025-08-24T10:06:42",
    "endDate": "2025-08-24T13:06:42",
    "createdAt": "2025-08-19T10:06:42",
    "updatedAt": "2025-08-23T10:06:42",
    "backgroundColor": "gray",
    "isAllDay": false,
    "repeatRule": "매주",
    "hasRepeatEndDate": true,
    "repeatEndDate": "2025-09-18T10:06:42",
    "isCompleted": true
  },
  {
    "id": "6fc7846c-2ba7-402f-902e-ac705cab250c",
    "title": "책 읽기",
    "startDate": "2025-09-19T09:39:37",
    "endDate": "2025-09-19T11:39:37",
    "createdAt": "2025-08-31T09:39:37",
    "updatedAt": "2025-09-15T09:39:37",
    "backgroundColor": "red",
    "isAllDay": true,
    "repeatRule": "매일",
    "hasRepeatEndDate": true,
    "repeatEndDate": "2025-10-10T09:39:37",
    "isCompleted": true
  },
  {
    "id": "1681024c-3ebd-470f-b37e-fdd3896c869a",
    "title": "수영",
    "startDate": "2025-08-24T17:53:29",
    "endDate": "2025-08-24T19:53:29",
    "createdAt": "2025-08-15T17:53:29",
    "updatedAt": "2025-08-21T17:53:29",
    "backgroundColor": "purple",
    "isAllDay": false,
    "repeatRule": null,
    "hasRepeatEndDate": false,
    "repeatEndDate": null,
    "isCompleted": false
  },
  {
    "id": "7b1f5495-18b9-4479-a674-68ba64c85ee1",
    "title": "발표 준비",
    "startDate": "2025-09-20T10:31:07",
    "endDate": "2025-09-20T13:31:07",
    "createdAt": "2025-09-10T10:31:07",
    "updatedAt": "2025-09-18T10:31:07",
    "backgroundColor": "red",
    "isAllDay": true,
    "repeatRule": "매주",
    "hasRepeatEndDate": true,
    "repeatEndDate": "2025-10-21T10:31:07",
    "isCompleted": true
  },
  {
    "id": "51a08277-5c89-4b62-9946-709c85892f04",
    "title": "퇴근",
    "startDate": "2025-08-09T14:46:37",
    "endDate": "2025-08-09T16:46:37",
    "createdAt": "2025-07-10T14:46:37",
    "updatedAt": "2025-08-09T14:46:37",
    "backgroundColor": "purple",
    "isAllDay": true,
    "repeatRule": null,
    "hasRepeatEndDate": false,
    "repeatEndDate": null,
    "isCompleted": true
  },
  {
    "id": "89eab904-348e-4177-998f-29d5b3bce72b",
    "title": "점심 약속",
    "startDate": "2025-09-05T20:39:35",
    "endDate": "2025-09-05T21:39:35",
    "createdAt": "2025-08-14T20:39:35",
    "updatedAt": "2025-09-04T20:39:35",
    "backgroundColor": "gray",
    "isAllDay": true,
    "repeatRule": "매주",
    "hasRepeatEndDate": true,
    "repeatEndDate": "2025-10-17T20:39:35",
    "isCompleted": true
  },
  {
    "id": "d6926dcc-0383-48d4-b85e-c81015616aa4",
    "title": "커피 타임",
    "startDate": "2025-07-28T22:14:20",
    "endDate": "2025-07-29T00:14:20",
    "createdAt": "2025-07-11T22:14:20",
    "updatedAt": "2025-07-26T22:14:20",
    "backgroundColor": "blue",
    "isAllDay": false,
    "repeatRule": "매일",
    "hasRepeatEndDate": false,
    "repeatEndDate": null,
    "isCompleted": false
  },
  {
    "id": "6a7f5d83-60f7-4d29-9a12-a60f2239d4ee",
    "title": "회의",
    "startDate": "2025-06-15T20:57:06",
    "endDate": "2025-06-15T23:57:06",
    "createdAt": "2025-05-27T20:57:06",
    "updatedAt": "2025-06-11T20:57:06",
    "backgroundColor": "pink",
    "isAllDay": false,
    "repeatRule": null,
    "hasRepeatEndDate": false,
    "repeatEndDate": null,
    "isCompleted": true
  },
  {
    "id": "7e31fe18-0d15-4732-9680-f04f0c9f825b",
    "title": "점심 약속",
    "startDate": "2025-09-04T13:12:40",
    "endDate": "2025-09-04T17:12:40",
    "createdAt": "2025-08-25T13:12:40",
    "updatedAt": "2025-09-02T13:12:40",
    "backgroundColor": "blue",
    "isAllDay": false,
    "repeatRule": "매일",
    "hasRepeatEndDate": false,
    "repeatEndDate": null,
    "isCompleted": true
  },
  {
    "id": "8132d088-d9a2-4b9f-8307-3029eda16569",
    "title": "자전거 타기",
    "startDate": "2025-08-07T22:49:46",
    "endDate": "2025-08-08T01:49:46",
    "createdAt": "2025-07-29T22:49:46",
    "updatedAt": "2025-08-05T22:49:46",
    "backgroundColor": "pink",
    "isAllDay": false,
    "repeatRule": null,
    "hasRepeatEndDate": false,
    "repeatEndDate": null,
    "isCompleted": true
  },
  {
    "id": "d0d60f38-baf4-436d-98fe-68229a74f5dd",
    "title": "개발 회의",
    "startDate": "2025-06-20T14:03:56",
    "endDate": "2025-06-20T17:03:56",
    "createdAt": "2025-05-22T14:03:56",
    "updatedAt": "2025-06-18T14:03:56",
    "backgroundColor": "gray",
    "isAllDay": false,
    "repeatRule": "매일",
    "hasRepeatEndDate": false,
    "repeatEndDate": null,
    "isCompleted": false
  },
  {
    "id": "c37ce51c-42f2-4eca-8286-8c8c93185a75",
    "title": "운동",
    "startDate": "2025-06-21T21:37:08",
    "endDate": "2025-06-22T00:37:08",
    "createdAt": "2025-06-08T21:37:08",
    "updatedAt": "2025-06-19T21:37:08",
    "backgroundColor": "blue",
    "isAllDay": false,
    "repeatRule": "매일",
    "hasRepeatEndDate": true,
    "repeatEndDate": "2025-07-01T21:37:08",
    "isCompleted": false
  },
  {
    "id": "ad301730-480f-46cb-9cc4-93514045fb70",
    "title": "점심 약속",
    "startDate": "2025-09-28T12:00:28",
    "endDate": "2025-09-28T14:00:28",
    "createdAt": "2025-08-30T12:00:28",
    "updatedAt": "2025-09-23T12:00:28",
    "backgroundColor": "orange",
    "isAllDay": false,
    "repeatRule": "매주",
    "hasRepeatEndDate": false,
    "repeatEndDate": null,
    "isCompleted": false
  },
  {
    "id": "bc433afc-1f85-4ec7-9db7-6035d17d3739",
    "title": "코딩",
    "startDate": "2025-06-12T10:16:44",
    "endDate": "2025-06-12T11:16:44",
    "createdAt": "2025-05-14T10:16:44",
    "updatedAt": "2025-06-10T10:16:44",
    "backgroundColor": "orange",
    "isAllDay": true,
    "repeatRule": null,
    "hasRepeatEndDate": false,
    "repeatEndDate": null,
    "isCompleted": false
  },
  {
    "id": "1b5a5494-9e27-42dd-8aa9-06ac8fc7ea6e",
    "title": "자전거 타기",
    "startDate": "2025-09-29T16:42:37",
    "endDate": "2025-09-29T19:42:37",
    "createdAt": "2025-09-01T16:42:37",
    "updatedAt": "2025-09-29T16:42:37",
    "backgroundColor": "gray",
    "isAllDay": true,
    "repeatRule": "매월",
    "hasRepeatEndDate": false,
    "repeatEndDate": null,
    "isCompleted": true
  }
]
